.project
.pydevproject
CHANGES.txt
Contributors.txt
MANIFEST.in
PKG-INFO
README.txt
setup.cfg
setup.py
tw/__init__.py
tw.swfobject.egg-info/PKG-INFO
tw.swfobject.egg-info/SOURCES.txt
tw.swfobject.egg-info/dependency_links.txt
tw.swfobject.egg-info/entry_points.txt
tw.swfobject.egg-info/namespace_packages.txt
tw.swfobject.egg-info/not-zip-safe
tw.swfobject.egg-info/paster_plugins.txt
tw.swfobject.egg-info/requires.txt
tw.swfobject.egg-info/top_level.txt
tw/swfobject/__init__.py
tw/swfobject/release.py
tw/swfobject/samples.py
tw/swfobject/widgets.py
tw/swfobject/static/expressInstall.swf
tw/swfobject/static/index.html
tw/swfobject/static/index_dynamic.html
tw/swfobject/static/swfobject.js
tw/swfobject/static/test.swf
tw/swfobject/static/src/expressInstall.as
tw/swfobject/static/src/expressInstall.fla
tw/swfobject/static/src/swfobject.js