Metadata-Version: 1.0
Name: tw.swfobject
Version: 0.2dev-20090428
Summary: ToscaWidget wrapper for swfobject
Home-page: http://code.google.com/p/twswfobject
Author: Patrick McKinnon
Author-email: swfobject@txsv.com
License: UNKNOWN
Keywords: toscawidgets.widgets
Platform: UNKNOWN
Classifier: Development Status :: 4 - Beta
Classifier: Environment :: Web Environment
Classifier: Environment :: Web Environment :: ToscaWidgets
Classifier: Topic :: Software Development :: Libraries :: Python Modules
Classifier: Topic :: Software Development :: Widget Sets
Classifier: Intended Audience :: Developers
Classifier: Operating System :: OS Independent
Classifier: Programming Language :: Python
Classifier: Framework :: TurboGears :: Widgets
Classifier: License :: OSI Approved :: GNU Library or Lesser General Public License (LGPL)
